terra_py-0.0.0.dist-info/DESCRIPTION.rst
terra_py-0.0.0.dist-info/METADATA
terra_py-0.0.0.dist-info/RECORD
terra_py-0.0.0.dist-info/WHEEL
terra_py-0.0.0.dist-info/entry_points.txt
terra_py-0.0.0.dist-info/metadata.json
terra_py-0.0.0.dist-info/top_level.txt
terrapy/__init__.py
terrapy/const.py
terrapy/emit.py
terrapy/wrap.py
