Metadata-Version: 2.0
Name: terra-py
Version: 0.0.0
Summary: generate terraform json
Home-page: UNKNOWN
Author: dmr
Author-email: dradetsky@gmail.com
License: WTFPL
Keywords: terraform,hcl
Platform: UNKNOWN
Classifier: Development Status :: 3 - Alpha
Classifier: Intended Audience :: Developers
Classifier: License :: DFSG approved
Classifier: License :: Freely Distributable
Classifier: License :: Public Domain
Classifier: Natural Language :: English
Classifier: Programming Language :: Python :: 3
Classifier: Programming Language :: Python :: 3.6
Classifier: Topic :: Software Development :: Code Generators
Classifier: Topic :: System :: Systems Administration
Requires-Dist: attrs (>=17.2.0)
